{
  "BilledCost-C-000-M": {
    "Function": "Composite",
    "Reference": "BilledCost",
    "EntityType": "Column",
    "Notes": "",
    "ModelVersionIntroduced": "1.2",
    "Status": "Active",
    "ApplicabilityCriteria": [],
    "Type": "Static",
    "ValidationCriteria": {
      "MustSatisfy": "The BilledCost column adheres to the following requirements:",
      "Keyword": "MUST",
      "Requirement": {
        "CheckFunction": "AND",
        "Items": [
          {
            "CheckFunction": "CheckModelRule",
            "ModelRuleId": "BilledCost-C-001-M"
          },
          {
            "CheckFunction": "CheckModelRule",
            "ModelRuleId": "BilledCost-C-002-M"
          },
          {
            "CheckFunction": "CheckModelRule",
            "ModelRuleId": "BilledCost-C-003-M"
          },
          {
            "CheckFunction": "CheckModelRule",
            "ModelRuleId": "BilledCost-C-004-M"
          },
          {
            "CheckFunction": "CheckModelRule",
            "ModelRuleId": "BilledCost-C-005-C"
          },
          {
            "CheckFunction": "CheckModelRule",
            "ModelRuleId": "BilledCost-C-006-M"
          },
          {
            "CheckFunction": "CheckModelRule",
            "ModelRuleId": "BilledCost-C-007-M"
          }
        ]
      },
      "Condition": {},
      "Dependencies": [
        "CostAndUsage-D-006-M",
        "BilledCost-C-001-M",
        "BilledCost-C-002-M",
        "BilledCost-C-003-M",
        "BilledCost-C-004-M",
        "BilledCost-C-005-C",
        "BilledCost-C-006-M",
        "BilledCost-C-007-M"
      ]
    }
  },
  "BilledCost-C-001-M": {
    "Function": "Type",
    "EntityType": "Column",
    "Reference": "BilledCost",
    "Notes": "",
    "ModelVersionIntroduced": "1.2",
    "Status": "Active",
    "ApplicabilityCriteria": [],
    "Type": "Static",
    "ValidationCriteria": {
      "MustSatisfy": "BilledCost MUST be of type Decimal.",
      "Keyword": "MUST",
      "Requirement": {
        "CheckFunction": "TypeDecimal",
        "ColumnName": "BilledCost"
      },
      "Condition": {},
      "Dependencies": []
    }
  },
  "BilledCost-C-002-M": {
    "Function": "Format",
    "EntityType": "Column",
    "Reference": "BilledCost",
    "Notes": "",
    "ModelVersionIntroduced": "1.2",
    "Status": "Active",
    "ApplicabilityCriteria": [],
    "Type": "Static",
    "ValidationCriteria": {
      "MustSatisfy": "BilledCost MUST conform to NumericFormat requirements.",
      "Keyword": "MUST",
      "Requirement": {
        "CheckFunction": "FormatNumeric",
        "ColumnName": "BilledCost"
      },
      "Condition": {},
      "Dependencies": []
    }
  },
  "BilledCost-C-003-M": {
    "Function": "Nullability",
    "Reference": "BilledCost",
    "EntityType": "Column",
    "Notes": "",
    "ModelVersionIntroduced": "1.2",
    "Status": "Active",
    "ApplicabilityCriteria": [],
    "Type": "Static",
    "ValidationCriteria": {
      "MustSatisfy": "BilledCost MUST NOT be null.",
      "Keyword": "MUST NOT",
      "Requirement": {
        "CheckFunction": "CheckNotValue",
        "ColumnName": "BilledCost",
        "Value": null
      },
      "Condition": {},
      "Dependencies": []
    }
  },
  "BilledCost-C-004-M": {
    "Function": "Validation",
    "Reference": "BilledCost",
    "EntityType": "Column",
    "Notes": "",
    "ModelVersionIntroduced": "1.2",
    "Status": "Active",
    "ApplicabilityCriteria": [],
    "Type": "Static",
    "ValidationCriteria": {
      "MustSatisfy": "BilledCost MUST be a valid decimal value.",
      "Keyword": "MUST",
      "Requirement": {
        "CheckFunction": "CheckDecimalValue",
        "ColumnName": "BilledCost"
      },
      "Condition": {},
      "Dependencies": []
    }
  },
  "BilledCost-C-005-C": {
    "Function": "Validation",
    "Reference": "BilledCost",
    "EntityType": "Column",
    "Notes": "",
    "ModelVersionIntroduced": "1.2",
    "Status": "Active",
    "ApplicabilityCriteria": [],
    "Type": "Static",
    "ValidationCriteria": {
      "MustSatisfy": "BilledCost MUST be 0 for charges where payments are received by a third party (e.g., marketplace transactions).",
      "Keyword": "MUST",
      "Requirement": {
        "CheckFunction": "CheckValue",
        "ColumnName": "BilledCost",
        "Value": 0
      },
      "Condition": {
        "CheckFunction": "CheckNotSameValue",
        "ColumnAName": "ProviderName",
        "ColumnBName": "InvoiceIssuerName"
      },
      "Dependencies": [
        "ProviderName-C-000-M",
        "InvoiceIssuerName-C-000-M"
      ]
    }
  },
  "BilledCost-C-006-M": {
    "Function": "Validation",
    "Reference": "BilledCost",
    "EntityType": "Column",
    "Notes": "",
    "ModelVersionIntroduced": "1.2",
    "Status": "Active",
    "ApplicabilityCriteria": [],
    "Type": "Dynamic",
    "ValidationCriteria": {
      "MustSatisfy": "BilledCost MUST be denominated in the BillingCurrency.",
      "Keyword": "MUST",
      "Requirement": {},
      "Condition": {},
      "Dependencies": []
    }
  },
  "BilledCost-C-007-M": {
    "Function": "Validation",
    "Reference": "BilledCost",
    "EntityType": "Column",
    "Notes": "",
    "ModelVersionIntroduced": "1.2",
    "Status": "Active",
    "ApplicabilityCriteria": [],
    "Type": "Dynamic",
    "ValidationCriteria": {
      "MustSatisfy": "The sum of the BilledCost for a given InvoiceId MUST match the sum of the payable amount provided in the corresponding invoice with the same id generated by the InvoiceIssuer.",
      "Keyword": "MUST",
      "Requirement": {},
      "Condition": {},
      "Dependencies": []
    }
  }
}